aineed-0.1.12.dist-info/METADATA
aineed-0.1.12.dist-info/WHEEL
aineed-0.1.12.dist-info/entry_points.txt
aineed/__init__.py
aineed/aineed.cpython-311-darwin.so
aineed-0.1.12.dist-info/RECORD
