Metadata-Version: 2.3
Name: aineed
Version: 0.1.12
Classifier: Development Status :: 4 - Beta
Classifier: Environment :: Console
Classifier: Intended Audience :: Developers
Classifier: License :: OSI Approved :: MIT License
Classifier: Programming Language :: Python :: 3
Classifier: Programming Language :: Python :: 3.8
Classifier: Programming Language :: Python :: 3.9
Classifier: Programming Language :: Python :: 3.10
Classifier: Programming Language :: Python :: 3.11
Classifier: Programming Language :: Rust
Classifier: Topic :: Software Development :: Libraries :: Python Modules
Summary: AI assistant CLI tool for multiple providers
Keywords: ai,cli,openai,anthropic,togetherai,openrouter,google,text generation,image generation,llm
Author: Nbiish <nbiish@umich.edu>
Author-email: Nbiish <nbiish@umich.edu>
License: MIT
Requires-Python: >=3.8
Project-URL: Source Code, https://github.com/nbiish/aineed
